{"children":[],"start":1,"end":612,"doc":{"children":null,"start":0,"end":0,"Comments":null},"package":1,"name":{"children":[],"start":9,"end":12,"NamePos":9,"Name":"ast","Object":null},"declarations":[{"children":[],"start":91,"end":407,"doc":{"children":null,"start":0,"end":0,"Comments":null},"tokenPosition":91,"token":84,"lparen":0,"specifications":[{"children":[],"start":96,"end":407,"doc":{"children":null,"start":0,"end":0,"Comments":null},"name":{"children":[],"start":96,"end":106,"NamePos":96,"Name":"CaseClause","Object":null},"typeParams":{"children":null,"start":0,"end":0,"opening":0,"list":null,"closing":0},"assign":0,"type":{"children":[],"start":107,"end":407,"struct":107,"fields":{"children":[],"start":114,"end":407,"opening":114,"list":[{"children":[],"start":117,"end":121,"doc":{"children":null,"start":0,"end":0,"Comments":null},"names":null,"type":{"children":[],"start":117,"end":121,"NamePos":117,"Name":"Node","Object":null},"tag":{"children":null,"start":0,"end":0,"valuePos":0,"kind":0,"value":""},"comment":{"children":null,"start":0,"end":0,"Comments":null}},{"children":[],"start":123,"end":155,"doc":{"children":null,"start":0,"end":0,"Comments":null},"names":[{"children":[],"start":123,"end":127,"NamePos":123,"Name":"Case","Object":null}],"type":{"children":[],"start":129,"end":132,"NamePos":129,"Name":"int","Object":null},"tag":{"children":[],"start":142,"end":155,"valuePos":142,"kind":9,"value":"`json:\"case\"`"},"comment":{"children":null,"start":0,"end":0,"Comments":null}},{"children":[],"start":201,"end":233,"doc":{"children":null,"start":0,"end":0,"Comments":null},"names":[{"children":[],"start":201,"end":205,"NamePos":201,"Name":"List","Object":null}],"type":{"children":[],"start":207,"end":219,"leftBracket":207,"length":null,"element":{"children":[],"start":209,"end":219,"NamePos":209,"Name":"Expression","Object":null}},"tag":{"children":[],"start":220,"end":233,"valuePos":220,"kind":9,"value":"`json:\"list\"`"},"comment":{"children":null,"start":0,"end":0,"Comments":null}},{"children":[],"start":292,"end":325,"doc":{"children":null,"start":0,"end":0,"Comments":null},"names":[{"children":[],"start":292,"end":297,"NamePos":292,"Name":"Colon","Object":null}],"type":{"children":[],"start":298,"end":301,"NamePos":298,"Name":"int","Object":null},"tag":{"children":[],"start":311,"end":325,"valuePos":311,"kind":9,"value":"`json:\"colon\"`"},"comment":{"children":null,"start":0,"end":0,"Comments":null}},{"children":[],"start":346,"end":378,"doc":{"children":null,"start":0,"end":0,"Comments":null},"names":[{"children":[],"start":346,"end":350,"NamePos":346,"Name":"Body","Object":null}],"type":{"children":[],"start":352,"end":363,"leftBracket":352,"length":null,"element":{"children":[],"start":354,"end":363,"NamePos":354,"Name":"Statement","Object":null}},"tag":{"children":[],"start":365,"end":378,"valuePos":365,"kind":9,"value":"`json:\"body\"`"},"comment":{"children":null,"start":0,"end":0,"Comments":null}}],"closing":406},"incomplete":false},"comment":{"children":null,"start":0,"end":0,"Comments":null}}],"rparen":0},{"children":[],"start":409,"end":459,"doc":{"children":null,"start":0,"end":0,"Comments":null},"receiver":{"children":[],"start":414,"end":428,"opening":414,"list":[{"children":[],"start":415,"end":427,"doc":{"children":null,"start":0,"end":0,"Comments":null},"names":[{"children":[],"start":415,"end":416,"NamePos":415,"Name":"s","Object":null}],"type":{"children":[],"start":417,"end":427,"NamePos":417,"Name":"CaseClause","Object":null},"tag":{"children":null,"start":0,"end":0,"valuePos":0,"kind":0,"value":""},"comment":{"children":null,"start":0,"end":0,"Comments":null}}],"closing":427},"name":{"children":[],"start":429,"end":434,"NamePos":429,"Name":"Start","Object":null},"type":{"children":[],"start":409,"end":440,"Function":409,"TypeParams":{"children":null,"start":0,"end":0,"opening":0,"list":null,"closing":0},"Params":{"children":[],"start":434,"end":436,"opening":434,"list":[],"closing":435},"Results":{"children":[],"start":437,"end":440,"opening":0,"list":[{"children":[],"start":437,"end":440,"doc":{"children":null,"start":0,"end":0,"Comments":null},"names":null,"type":{"children":[],"start":437,"end":440,"NamePos":437,"Name":"int","Object":null},"tag":{"children":null,"start":0,"end":0,"valuePos":0,"kind":0,"value":""},"comment":{"children":null,"start":0,"end":0,"Comments":null}}],"closing":0}},"body":{"children":[],"start":441,"end":459,"lbrace":441,"list":[{"children":[],"start":444,"end":457,"return":444,"results":[{"children":[],"start":451,"end":457,"expression":{"children":[],"start":451,"end":452,"NamePos":451,"Name":"s","Object":null},"sel":{"children":[],"start":453,"end":457,"NamePos":453,"Name":"Case","Object":null}}]}],"rbrace":458}},{"children":[],"start":461,"end":574,"doc":{"children":null,"start":0,"end":0,"Comments":null},"receiver":{"children":[],"start":466,"end":480,"opening":466,"list":[{"children":[],"start":467,"end":479,"doc":{"children":null,"start":0,"end":0,"Comments":null},"names":[{"children":[],"start":467,"end":468,"NamePos":467,"Name":"s","Object":null}],"type":{"children":[],"start":469,"end":479,"NamePos":469,"Name":"CaseClause","Object":null},"tag":{"children":null,"start":0,"end":0,"valuePos":0,"kind":0,"value":""},"comment":{"children":null,"start":0,"end":0,"Comments":null}}],"closing":479},"name":{"children":[],"start":481,"end":484,"NamePos":481,"Name":"End","Object":null},"type":{"children":[],"start":461,"end":490,"Function":461,"TypeParams":{"children":null,"start":0,"end":0,"opening":0,"list":null,"closing":0},"Params":{"children":[],"start":484,"end":486,"opening":484,"list":[],"closing":485},"Results":{"children":[],"start":487,"end":490,"opening":0,"list":[{"children":[],"start":487,"end":490,"doc":{"children":null,"start":0,"end":0,"Comments":null},"names":null,"type":{"children":[],"start":487,"end":490,"NamePos":487,"Name":"int","Object":null},"tag":{"children":null,"start":0,"end":0,"valuePos":0,"kind":0,"value":""},"comment":{"children":null,"start":0,"end":0,"Comments":null}}],"closing":0}},"body":{"children":[],"start":491,"end":574,"lbrace":491,"list":[{"children":[],"start":494,"end":552,"if":494,"initialization":{"children":[],"start":497,"end":513,"lhs":[{"children":[],"start":497,"end":498,"NamePos":497,"Name":"n","Object":null}],"tokenPos":499,"token":47,"rhs":[{"children":[],"start":502,"end":513,"function":{"children":[],"start":502,"end":505,"NamePos":502,"Name":"len","Object":null},"lparen":0,"args":[{"children":[],"start":506,"end":512,"expression":{"children":[],"start":506,"end":507,"NamePos":506,"Name":"s","Object":null},"sel":{"children":[],"start":508,"end":512,"NamePos":508,"Name":"Body","Object":null}}],"ellipsis":0,"rparen":0}]},"condition":{"children":[],"start":515,"end":520,"leftExpression":{"children":[],"start":515,"end":516,"NamePos":515,"Name":"n","Object":null},"opPos":517,"op":41,"rightExpression":{"children":[],"start":519,"end":520,"valuePos":519,"kind":5,"value":"0"}},"body":{"children":[],"start":521,"end":552,"lbrace":521,"list":[{"children":[],"start":525,"end":549,"return":525,"results":[{"children":[],"start":532,"end":549,"function":{"children":[],"start":532,"end":547,"expression":{"children":[],"start":532,"end":543,"expression":{"children":[],"start":532,"end":538,"expression":{"children":[],"start":532,"end":533,"NamePos":532,"Name":"s","Object":null},"sel":{"children":[],"start":534,"end":538,"NamePos":534,"Name":"Body","Object":null}},"leftBracket":538,"index":{"children":[],"start":539,"end":542,"leftExpression":{"children":[],"start":539,"end":540,"NamePos":539,"Name":"n","Object":null},"opPos":540,"op":13,"rightExpression":{"children":[],"start":541,"end":542,"valuePos":541,"kind":5,"value":"1"}},"rightBracket":542},"sel":{"children":[],"start":544,"end":547,"NamePos":544,"Name":"End","Object":null}},"lparen":0,"args":[],"ellipsis":0,"rparen":0}]}],"rbrace":551},"else":null},{"children":[],"start":554,"end":572,"return":554,"results":[{"children":[],"start":561,"end":572,"leftExpression":{"children":[],"start":561,"end":568,"expression":{"children":[],"start":561,"end":562,"NamePos":561,"Name":"s","Object":null},"sel":{"children":[],"start":563,"end":568,"NamePos":563,"Name":"Colon","Object":null}},"opPos":569,"op":12,"rightExpression":{"children":[],"start":571,"end":572,"valuePos":571,"kind":5,"value":"1"}}]}],"rbrace":573}},{"children":[],"start":576,"end":612,"doc":{"children":null,"start":0,"end":0,"Comments":null},"receiver":{"children":[],"start":581,"end":593,"opening":581,"list":[{"children":[],"start":582,"end":592,"doc":{"children":null,"start":0,"end":0,"Comments":null},"names":null,"type":{"children":[],"start":582,"end":592,"NamePos":582,"Name":"CaseClause","Object":null},"tag":{"children":null,"start":0,"end":0,"valuePos":0,"kind":0,"value":""},"comment":{"children":null,"start":0,"end":0,"Comments":null}}],"closing":592},"name":{"children":[],"start":594,"end":607,"NamePos":594,"Name":"StatementNode","Object":null},"type":{"children":[],"start":576,"end":609,"Function":576,"TypeParams":{"children":null,"start":0,"end":0,"opening":0,"list":null,"closing":0},"Params":{"children":[],"start":607,"end":609,"opening":607,"list":[],"closing":608},"Results":{"children":null,"start":0,"end":0,"opening":0,"list":null,"closing":0}},"body":{"children":[],"start":610,"end":612,"lbrace":610,"list":[],"rbrace":611}}],"fileStart":1,"fileEnd":613,"scope":{"outer":null,"objects":null},"imports":[],"unresolved":[],"comments":[],"goVersion":""}