{"children":[],"start":1,"end":389,"doc":{"children":null,"start":0,"end":0,"Comments":null},"package":1,"name":{"children":[],"start":9,"end":12,"NamePos":9,"Name":"ast","Object":null},"declarations":[{"children":[],"start":120,"end":389,"doc":{"children":null,"start":0,"end":0,"Comments":null},"tokenPosition":120,"token":84,"lparen":0,"specifications":[{"children":[],"start":125,"end":389,"doc":{"children":null,"start":0,"end":0,"Comments":null},"name":{"children":[],"start":125,"end":134,"NamePos":125,"Name":"FieldList","Object":null},"typeParams":{"children":null,"start":0,"end":0,"opening":0,"list":null,"closing":0},"assign":0,"type":{"children":[],"start":135,"end":389,"struct":135,"fields":{"children":[],"start":142,"end":389,"opening":142,"list":[{"children":[],"start":145,"end":149,"doc":{"children":null,"start":0,"end":0,"Comments":null},"names":null,"type":{"children":[],"start":145,"end":149,"NamePos":145,"Name":"Node","Object":null},"tag":{"children":null,"start":0,"end":0,"valuePos":0,"kind":0,"value":""},"comment":{"children":null,"start":0,"end":0,"Comments":null}},{"children":[],"start":151,"end":183,"doc":{"children":null,"start":0,"end":0,"Comments":null},"names":[{"children":[],"start":151,"end":158,"NamePos":151,"Name":"Opening","Object":null}],"type":{"children":[],"start":159,"end":162,"NamePos":159,"Name":"int","Object":null},"tag":{"children":[],"start":167,"end":183,"valuePos":167,"kind":9,"value":"`json:\"opening\"`"},"comment":{"children":null,"start":0,"end":0,"Comments":null}},{"children":[],"start":242,"end":271,"doc":{"children":null,"start":0,"end":0,"Comments":null},"names":[{"children":[],"start":242,"end":246,"NamePos":242,"Name":"List","Object":null}],"type":{"children":[],"start":250,"end":257,"leftBracket":250,"length":null,"element":{"children":[],"start":252,"end":257,"NamePos":252,"Name":"Field","Object":null}},"tag":{"children":[],"start":258,"end":271,"valuePos":258,"kind":9,"value":"`json:\"list\"`"},"comment":{"children":null,"start":0,"end":0,"Comments":null}},{"children":[],"start":298,"end":330,"doc":{"children":null,"start":0,"end":0,"Comments":null},"names":[{"children":[],"start":298,"end":305,"NamePos":298,"Name":"Closing","Object":null}],"type":{"children":[],"start":306,"end":309,"NamePos":306,"Name":"int","Object":null},"tag":{"children":[],"start":314,"end":330,"valuePos":314,"kind":9,"value":"`json:\"closing\"`"},"comment":{"children":null,"start":0,"end":0,"Comments":null}}],"closing":388},"incomplete":false},"comment":{"children":null,"start":0,"end":0,"Comments":null}}],"rparen":0}],"fileStart":1,"fileEnd":390,"scope":{"outer":null,"objects":null},"imports":[],"unresolved":[],"comments":[],"goVersion":""}