{"children":[],"start":1,"end":185,"doc":{"children":null,"start":0,"end":0,"Comments":null},"package":1,"name":{"children":[],"start":9,"end":12,"NamePos":9,"Name":"ast","Object":null},"declarations":[{"children":[],"start":125,"end":185,"doc":{"children":null,"start":0,"end":0,"Comments":null},"tokenPosition":125,"token":84,"lparen":0,"specifications":[{"children":[],"start":130,"end":185,"doc":{"children":null,"start":0,"end":0,"Comments":null},"name":{"children":[],"start":130,"end":143,"NamePos":130,"Name":"Specification","Object":null},"typeParams":{"children":null,"start":0,"end":0,"opening":0,"list":null,"closing":0},"assign":0,"type":{"children":[],"start":144,"end":185,"interface":144,"methods":{"children":[],"start":154,"end":185,"opening":154,"list":[{"children":[],"start":157,"end":162,"doc":{"children":null,"start":0,"end":0,"Comments":null},"names":null,"type":{"children":[],"start":157,"end":162,"NamePos":157,"Name":"INode","Object":null},"tag":{"children":null,"start":0,"end":0,"valuePos":0,"kind":0,"value":""},"comment":{"children":null,"start":0,"end":0,"Comments":null}},{"children":[],"start":164,"end":183,"doc":{"children":null,"start":0,"end":0,"Comments":null},"names":[{"children":[],"start":164,"end":181,"NamePos":164,"Name":"specificationNode","Object":null}],"type":{"children":[],"start":181,"end":183,"Function":0,"TypeParams":{"children":null,"start":0,"end":0,"opening":0,"list":null,"closing":0},"Params":{"children":[],"start":181,"end":183,"opening":181,"list":[],"closing":182},"Results":{"children":null,"start":0,"end":0,"opening":0,"list":null,"closing":0}},"tag":{"children":null,"start":0,"end":0,"valuePos":0,"kind":0,"value":""},"comment":{"children":null,"start":0,"end":0,"Comments":null}}],"closing":184},"incomplete":false},"comment":{"children":null,"start":0,"end":0,"Comments":null}}],"rparen":0}],"fileStart":1,"fileEnd":186,"scope":{"outer":null,"objects":null},"imports":[],"unresolved":[],"comments":[],"goVersion":""}